ultrack/__init__.py
ultrack/conftest.py
ultrack/napari.yaml
ultrack/api/__init__.py
ultrack/api/app.py
ultrack/api/database.py
ultrack/api/main.py
ultrack/api/settings.py
ultrack/api/_test/test_api.py
ultrack/api/utils/__init__.py
ultrack/api/utils/api.py
ultrack/api/utils/fs.py
ultrack/api/utils/zarr.py
ultrack/cli/__init__.py
ultrack/cli/check_gurobi.py
ultrack/cli/clear_database.py
ultrack/cli/config.py
ultrack/cli/data_summary.py
ultrack/cli/estimate_params.py
ultrack/cli/export.py
ultrack/cli/flow.py
ultrack/cli/labels_to_edges.py
ultrack/cli/link.py
ultrack/cli/main.py
ultrack/cli/match_gt.py
ultrack/cli/predict.py
ultrack/cli/segment.py
ultrack/cli/server.py
ultrack/cli/solve.py
ultrack/cli/utils.py
ultrack/cli/view.py
ultrack/cli/_test/test_cli.py
ultrack/config/README.md
ultrack/config/__init__.py
ultrack/config/config.py
ultrack/config/dataconfig.py
ultrack/config/segmentationconfig.py
ultrack/config/trackingconfig.py
ultrack/config/_test/test_config.py
ultrack/core/README.md
ultrack/core/__init__.py
ultrack/core/database.py
ultrack/core/interactive.py
ultrack/core/main.py
ultrack/core/match_gt.py
ultrack/core/tracker.py
ultrack/core/_test/test_database.py
ultrack/core/_test/test_gt_matching.py
ultrack/core/_test/test_interactive.py
ultrack/core/_test/test_main.py
ultrack/core/_test/test_tracker.py
ultrack/core/export/__init__.py
ultrack/core/export/ctc.py
ultrack/core/export/exporter.py
ultrack/core/export/geff.py
ultrack/core/export/networkx.py
ultrack/core/export/trackmate.py
ultrack/core/export/tracks_layer.py
ultrack/core/export/utils.py
ultrack/core/export/zarr.py
ultrack/core/export/_test/test_ctc.py
ultrack/core/export/_test/test_exporter.py
ultrack/core/export/_test/test_geff.py
ultrack/core/export/_test/test_networkx.py
ultrack/core/export/_test/test_trackmate.py
ultrack/core/linking/__init__.py
ultrack/core/linking/features.py
ultrack/core/linking/processing.py
ultrack/core/linking/utils.py
ultrack/core/linking/_test/test_link_processing.py
ultrack-0.7.1.dist-info/METADATA
ultrack-0.7.1.dist-info/WHEEL
ultrack-0.7.1.dist-info/entry_points.txt
ultrack-0.7.1.dist-info/licenses/LICENSE
ultrack-0.7.1.dist-info/RECORD
