Metadata-Version: 2.4
Name: ultrack
Version: 0.7.1
Summary: Large-scale multi-hypotheses cell tracking
Author-email: Jordao Bragantini <jordao.bragantini@czbiohub.org>
License-Expression: BSD-3-Clause
License-File: LICENSE
Classifier: Framework :: napari
Classifier: Intended Audience :: Science/Research
Classifier: License :: OSI Approved :: BSD License
Classifier: Programming Language :: Python
Classifier: Programming Language :: Python :: 3.9
Classifier: Programming Language :: Python :: 3.10
Classifier: Programming Language :: Python :: 3.11
Classifier: Programming Language :: Python :: 3.12
Classifier: Topic :: Scientific/Engineering
Classifier: Topic :: Scientific/Engineering :: Artificial Intelligence
Classifier: Topic :: Scientific/Engineering :: Image Processing
Requires-Python: <3.13,>=3.9
Requires-Dist: blosc2>=2.2.0
Requires-Dist: click>=8.1.3
Requires-Dist: cloudpickle>=3.0.0
Requires-Dist: edt>=2.3.2
Requires-Dist: fastapi>=0.109.2
Requires-Dist: fasteners>=0.20
Requires-Dist: geff>=1.0.0
Requires-Dist: gurobipy!=12.0.0,>=9.0.0
Requires-Dist: higra>=0.6.10
Requires-Dist: httpx>=0.26.0
Requires-Dist: imagecodecs>=2023.3.16
Requires-Dist: imageio>=2.28.0
Requires-Dist: magicgui>=0.7.2
Requires-Dist: mip>=1.16rc0
Requires-Dist: napari>=0.4.18
Requires-Dist: numba>=0.57.0
Requires-Dist: numcodecs
Requires-Dist: ome-zarr>=0.9.0
Requires-Dist: pandas>=2.0.1
Requires-Dist: pillow>=10.0.0
Requires-Dist: psycopg2-binary>=2.9.6
Requires-Dist: psygnal>=0.9.0
Requires-Dist: pyarrow<20,>=16.1.0
Requires-Dist: pydantic-settings
Requires-Dist: pydantic>=2.11.0
Requires-Dist: pydot>=2.0.0
Requires-Dist: qtawesome>=1.3.1
Requires-Dist: qtpy
Requires-Dist: rich>=13.3.5
Requires-Dist: scikit-image>=0.23.0
Requires-Dist: seaborn>=0.13.0
Requires-Dist: sqlalchemy>=2.0.0
Requires-Dist: toml>=0.10.2
Requires-Dist: torch>=2.0.1
Requires-Dist: urllib3
Requires-Dist: uvicorn>=0.27.0.post1
Requires-Dist: websockets>=12.0
Requires-Dist: zarr>=3.0.0
Provides-Extra: docs
Requires-Dist: autodoc-pydantic; extra == 'docs'
Requires-Dist: furo; extra == 'docs'
Requires-Dist: myst-parser>=2.0.0; extra == 'docs'
Requires-Dist: nbsphinx>=0.9.3; extra == 'docs'
Requires-Dist: sphinx-click<6.0.0,>=5.0.1; extra == 'docs'
Requires-Dist: sphinx-copybutton; extra == 'docs'
Requires-Dist: sphinx-gallery==0.15.0; extra == 'docs'
Requires-Dist: sphinx==6.2.1; extra == 'docs'
Requires-Dist: sphinxcontrib-applehelp==1.0.8; extra == 'docs'
Provides-Extra: ml
Requires-Dist: catboost>=1.2.7; extra == 'ml'
Requires-Dist: scikit-learn>=1.6.0; extra == 'ml'
Provides-Extra: test
Requires-Dist: asv>=0.5.1; extra == 'test'
Requires-Dist: napari[testing]>0.4.18; extra == 'test'
Requires-Dist: pre-commit>=3.2.2; extra == 'test'
Requires-Dist: pyqt5>=5.15.4; extra == 'test'
Requires-Dist: pytest-qt>=4.2.0; extra == 'test'
Requires-Dist: pytest>=7.3.1; extra == 'test'
Requires-Dist: pytrackmate>=1.3.4; extra == 'test'
